symbolix/__init__.py
symbolix-0.0.1.dist-info/METADATA
symbolix-0.0.1.dist-info/WHEEL
symbolix-0.0.1.dist-info/licenses/LICENSE
symbolix-0.0.1.dist-info/RECORD
